flake8_consistent_quotes/__init__.py
flake8_consistent_quotes/checker.py
flake8_consistent_quotes-0.1.2.dist-info/LICENSE.md
flake8_consistent_quotes-0.1.2.dist-info/METADATA
flake8_consistent_quotes-0.1.2.dist-info/WHEEL
flake8_consistent_quotes-0.1.2.dist-info/entry_points.txt
flake8_consistent_quotes-0.1.2.dist-info/RECORD
